sakuraParisAPI/__init__.py
sakuraParisAPI/sakura.py
sakuraParisAPI/fetch/__init__.py
sakuraParisAPI/fetch/entryClass.py
sakuraParisAPI/fetch/query.py
sakuraParisAPI-0.1.1.dist-info/LICENSE
sakuraParisAPI-0.1.1.dist-info/METADATA
sakuraParisAPI-0.1.1.dist-info/WHEEL
sakuraParisAPI-0.1.1.dist-info/top_level.txt
sakuraParisAPI-0.1.1.dist-info/RECORD
